MANIFEST.in
README.md
requirements.txt
setup.py
django_yx_app.egg-info/PKG-INFO
django_yx_app.egg-info/SOURCES.txt
django_yx_app.egg-info/dependency_links.txt
django_yx_app.egg-info/requires.txt
django_yx_app.egg-info/top_level.txt
yx/__init__.py
yx/admin.py
yx/djangohelper.py
yx/models.py
yx/sdkhelper.py
yx/search.py
yx/testbase.py
yx/tests.py
yx/utils.py
yx/views.py
yx/management/__init__.py
yx/management/commands/__init__.py
yx/management/commands/download_single_note.py
yx/management/commands/pull.py
yx/management/commands/pull_all_tags.py
yx/management/commands/pull_single_note.py
yx/management/commands/push.py
yx/management/commands/update_all_tags.py
yx/sync/__init__.py
yx/sync/exceptions.py
yx/sync/fullsync.py
yx/sync/notebooks.py
yx/sync/notes.py
yx/sync/searches.py
yx/sync/tags.py
yx/sync/typeconverters.py