Metadata-Version: 2.1
Name: django-yx-app
Version: 0.0.4
Summary: evernote helper app of django
Home-page: https://github.com/axplus/django_yx_app
Author: yijie zeng
Author-email: axplus@163.com
License: UNKNOWN
Platform: UNKNOWN
Classifier: Programming Language :: Python :: 2
Classifier: License :: OSI Approved :: MIT License
Classifier: Operating System :: OS Independent
Requires-Python: >=2.6
